kwrappers/__init__.py
kwrappers_dynamodb-0.2.data/data/requirements.txt
kwrappers_dynamodb-0.2.data/data/version.txt
kwrappers_dynamodb-0.2.dist-info/METADATA
kwrappers_dynamodb-0.2.dist-info/RECORD
kwrappers_dynamodb-0.2.dist-info/WHEEL
kwrappers_dynamodb-0.2.dist-info/entry_points.txt
kwrappers_dynamodb-0.2.dist-info/top_level.txt
